restfw_composed_permissions/__init__.py
restfw_composed_permissions/base.py
restfw_composed_permissions/models.py
restfw_composed_permissions/generic/__init__.py
restfw_composed_permissions/generic/components.py
restfw_composed_permissions/generic/permissions.py
restfw_composed_permissions/tests/__init__.py
restfw_composed_permissions/tests/settings_sqlite.py
restfw_composed_permissions/tests/tests.py
djangorestframework_composed_permissions-0.2.1.dist-info/LICENSE
djangorestframework_composed_permissions-0.2.1.dist-info/METADATA
djangorestframework_composed_permissions-0.2.1.dist-info/WHEEL
djangorestframework_composed_permissions-0.2.1.dist-info/top_level.txt
djangorestframework_composed_permissions-0.2.1.dist-info/RECORD
